MANIFEST.in
README.md
setup.cfg
setup.py
GpuCalculateTools.egg-info/PKG-INFO
GpuCalculateTools.egg-info/SOURCES.txt
GpuCalculateTools.egg-info/dependency_links.txt
GpuCalculateTools.egg-info/top_level.txt
GpuCalculateTools/includes/device_diagnose/device_properties.cu
GpuCalculateTools/includes/device_test/device_test_array.cu
GpuCalculateTools/GPUImplements/GpuDeviceProperties.py
GpuCalculateTools/GPUImplements/GpuDeviceTest.py
GpuCalculateTools/GPUImplements/__init__.py
GpuCalculateTools/GPUImplements/__pycache__/GpuDeviceProperties.cpython-310.pyc
GpuCalculateTools/GPUImplements/__pycache__/__init__.cpython-310.pyc
GpuCalculateTools/includes/device_diagnose/device_properties.cu
GpuCalculateTools/includes/device_diagnose/device_properties.h
GpuCalculateTools/includes/device_test/device_test_array.cu
GpuCalculateTools/includes/device_test/device_test_array.h
gpucalculatetools.egg-info/PKG-INFO
gpucalculatetools.egg-info/SOURCES.txt
gpucalculatetools.egg-info/dependency_links.txt
gpucalculatetools.egg-info/top_level.txt