Metadata-Version: 2.1
Name: gpucalculatetools
Version: 0.0.3
Summary: GpuCalculateTools is a data computation library developed based on the native Python C API and CUDA. Currently, the library is in testing and development. If you have any questions, please contact 1295284735@qq.com.
Author: adroit_fisherman
Author-email: 1295284735@qq.com
Platform: Windows
Classifier: Development Status :: 2 - Pre-Alpha
Classifier: Natural Language :: Chinese (Simplified)
Classifier: Operating System :: Microsoft :: Windows :: Windows 10
Classifier: Operating System :: Microsoft :: Windows :: Windows 11
Classifier: Programming Language :: C++
Classifier: Programming Language :: Python :: 3.12
Classifier: Programming Language :: Python :: 3.11
Classifier: Programming Language :: Python :: 3.10
Classifier: Programming Language :: Python :: 3.9
Classifier: Programming Language :: Python :: 3.8
Classifier: Programming Language :: Python :: 3.7
Classifier: Programming Language :: Python :: 3.6
Classifier: Topic :: Utilities
Requires-Python: >=3.6
